setup.py
ttyodist/Binomialdistribution.py
ttyodist/Gaussiandistribution.py
ttyodist/Generaldistribution.py
ttyodist/__init__.py
ttyodist.egg-info/PKG-INFO
ttyodist.egg-info/SOURCES.txt
ttyodist.egg-info/dependency_links.txt
ttyodist.egg-info/not-zip-safe
ttyodist.egg-info/top_level.txt