Metadata-Version: 1.0
Name: ttyodist
Version: 1.1
Summary: Gaussian and Binomial distributions
Home-page: UNKNOWN
Author: Thomas DuQuesnay
Author-email: UNKNOWN
License: UNKNOWN
Platform: UNKNOWN
